egproject/__init__.py
egproject/_main.py
egproject-0.0.29.dist-info/DESCRIPTION.rst
egproject-0.0.29.dist-info/METADATA
egproject-0.0.29.dist-info/RECORD
egproject-0.0.29.dist-info/WHEEL
egproject-0.0.29.dist-info/entry_points.txt
egproject-0.0.29.dist-info/metadata.json
egproject-0.0.29.dist-info/top_level.txt
