Metadata-Version: 2.0
Name: egproject
Version: 0.0.29
Summary: A Python package to print
Home-page: UNKNOWN
Author: ANOOP SINGH RANA
Author-email: apours986@gmail.com
License: MIT
Platform: UNKNOWN
Classifier: Programming Language :: Python :: 2.7
Requires-Dist: PIL
Requires-Dist: numpy
Requires-Dist: openpyxl
Requires-Dist: xlsxwriter
